pytest_defer.py
pytest_defer-0.2.1.dist-info/LICENSE
pytest_defer-0.2.1.dist-info/METADATA
pytest_defer-0.2.1.dist-info/WHEEL
pytest_defer-0.2.1.dist-info/top_level.txt
pytest_defer-0.2.1.dist-info/RECORD
