Metadata-Version: 2.1
Name: pytest_defer
Version: 0.2.1
Summary: A 'defer' fixture for pytest
Author-email: Miki Tebeka <miki@353solutions.com>
License: MIT License
Keywords: testing,pytest
Requires-Python: >=3.12
License-File: LICENSE
Requires-Dist: pytest >=8.3
